LICENSE
README.md
setup.cfg
setup.py
ohmic/__init__.py
ohmic/metrics.py
ohmic.egg-info/PKG-INFO
ohmic.egg-info/SOURCES.txt
ohmic.egg-info/dependency_links.txt
ohmic.egg-info/not-zip-safe
ohmic.egg-info/requires.txt
ohmic.egg-info/top_level.txt