Metadata-Version: 2.1
Name: ohmic
Version: 0.1.2
Summary: Python tools for Electric Power Quality
Home-page: UNKNOWN
License: apache-2.0
Platform: UNKNOWN
